{
  "folder": "C8SqgGKH0jyte25m",
  "name": "Bone Shaper",
  "type": "feat",
  "effects": [],
  "system": {
    "description": {
      "gm": "",
      "value": "<p>Bone shapers, also known as osteomancers, craft what they desire from the skeletons of the dead or simply create new skeletons by expanding and shaping small bone pieces.</p><p><strong>Class Feat</strong> Bone Spear</p><p><strong>General Feat</strong> @UUID[Compendium.pf2e.feats-srd.Item.Ux73dmoF8KnavyUD]{Fleet}</p><p><strong>Thrall Enhancement</strong> Your thralls are well constructed and nimble. Whenever one or more of your thralls would take damage from an effect requiring a Reflex save, you can attempt a @Check[flat|dc:15]. If you succeed, you choose one thrall to take no damage, and on a critical success none of the thralls take the damage.</p>"
    },
    "rules": [
      {
        "key": "GrantItem",
        "uuid": "Compendium.pf2e.feats-srd.Item.Ux73dmoF8KnavyUD"
      }
    ],
    "slug": null,
    "_migration": {
      "version": 0.935,
      "lastMigration": null
    },
    "traits": {
      "otherTags": [
        "necromancer-grim-fascination"
      ],
      "value": [
        "necromancer"
      ],
      "rarity": "common"
    },
    "publication": {
      "title": "Pathfinder Impossible Playtest",
      "authors": "",
      "license": "ORC",
      "remaster": true
    },
    "level": {
      "value": 1
    },
    "category": "classfeature",
    "onlyLevel1": false,
    "maxTakable": 1,
    "actionType": {
      "value": "passive"
    },
    "actions": {
      "value": null
    },
    "prerequisites": {
      "value": []
    },
    "location": null
  },
  "_id": "reIgmkq7JCDtnvsJ",
  "img": "icons/magic/death/undead-skeleton-energy-green.webp",
  "sort": 0,
  "ownership": {
    "default": 0,
    "xrkQVtB9iGZvxqph": 3
  },
  "flags": {},
  "_stats": {
    "compendiumSource": null,
    "duplicateSource": null,
    "coreVersion": "12.331",
    "systemId": "pf2e",
    "systemVersion": "6.7.2"
  },
  "_key": "!items!reIgmkq7JCDtnvsJ"
}
