{
  "folder": null,
  "name": "Crash Against Me",
  "type": "action",
  "effects": [],
  "system": {
    "description": {
      "gm": "",
      "value": "<p>Your skin becomes virtually unbreakable until the beginning of your next turn. Your resistance increases to a value equal to your level. During this time, if a creature fails a melee attack roll against you using a weapon dealing the same damage type as your resistance, or if they succeed at an attack against you with the weapon but your resistance would be enough to reduce the damage dealt to 0, that weapon clangs wildly off your skin with a painful reverberation, making the attacking enemy @Compendium[pf2e.conditionitems.Off-Guard]{Off-Guard} and applying a –2 circumstance penalty to attacks with that weapon until the beginning of their next turn.</p>"
    },
    "rules": [],
    "slug": null,
    "_migration": {
      "version": null,
      "lastMigration": null
    },
    "traits": {
      "otherTags": [],
      "value": []
    },
    "publication": {
      "title": "",
      "authors": "",
      "license": "OGL",
      "remaster": false
    },
    "actionType": {
      "value": "action"
    },
    "category": "offensive",
    "actions": {
      "value": 1
    },
    "deathNote": false,
    "source": {
      "value": "War of Immortals Class Playtest"
    },
    "schema": {
      "version": 0.857,
      "lastMigration": null
    },
    "requirements": {
      "value": ""
    },
    "trigger": {
      "value": ""
    }
  },
  "img": "systems/pf2e/icons/actions/OneAction.webp",
  "flags": {},
  "_stats": {
    "systemId": "pf2e",
    "systemVersion": "5.3.2",
    "coreVersion": "12.327",
    "createdTime": 1692992093518,
    "modifiedTime": 1693160212424,
    "lastModifiedBy": "CmdglLq38DpgHzdd",
    "compendiumSource": null,
    "duplicateSource": null
  },
  "_id": "q3odPW5lzuTNKp7x",
  "sort": 0,
  "ownership": {
    "default": 0,
    "CmdglLq38DpgHzdd": 3
  },
  "_key": "!items!q3odPW5lzuTNKp7x"
}
