{
  "folder": null,
  "name": "Vanguard of Roaring Waters",
  "type": "feat",
  "effects": [],
  "system": {
    "description": {
      "gm": "",
      "value": "<p>Vanguards of roaring waters are most commonly found where rivers carve their way through mountains, creating fearsome rapids. They can also be found near bays where rivers meet the sea and create turbulent breakers and unpredictable undertows. Vanguards of roaring waters encourage chaos and are easily bored. Apparition Skill Mountain Lore, River Lore</p>\n<h2>Apparition Spells</h2>\n<p><strong>Cantrip</strong> <em>@Compendium[pf2e.spells-srd.zhDIiQlJmrd4UDNC]{Rousing Splash}</em>; <strong>1st</strong> <em>@Compendium[pf2e.spells-srd.jfVCuOpzC6mUrf6f]{Hydraulic Push}</em>; <strong>2nd</strong> <em>@Compendium[pf2e.spells-srd.9XHmC2JgTUIQ1CCm]{Obscuring Mist}</em>; <strong>3rd</strong> <em>@Compendium[pf2e.spells-srd.oUDNCArkQTdhllxD]{Aqueous Orb}</em>; <strong>4th</strong> <em>@Compendium[pf2e.spells-srd.Y3G6Y6EDgCY0s3fq]{Hydraulic Torrent}</em>; <strong>5th</strong> <em>@Compendium[pf2e.spells-srd.zfn5RqAdF63neqpP]{Control Water}</em>; <strong>6th</strong> <em>@Compendium[pf2e.spells-srd.K2bTUhucPyhXlzjw]{Personal Ocean}</em>; <strong>7th</strong> <em>@Compendium[pf2e.spells-srd.smiVuoFMSgY2FTOO]{Dancing Fountain}</em>; <strong>8th</strong> <em>@Compendium[pf2e.spells-srd.0fjz8qc9NfkmWmJZ]{Whirlpool}</em>; <strong>9th</strong> <em>@Compendium[pf2e.spells-srd.yLJROsQtyrPIKcDx]{Wrathful Storm}</em></p>\n<h2>Vessel Spell</h2>\n<p><em>@Compendium[pf2e-playtest-data.war-of-immortals-playtest-spells.8cvXMUfgCxGZfhrI]{River Carving Mountains}</em></p>\n<h2>Avatar</h2>\n<p><strong>River that Splits the World</strong> Speed 50 feet, swim Speed 70 feet;</p>\n<p><strong>Melee</strong> <span class=\"pf2-icon\">1</span> parting mountains (versatile S, water), <strong>Damage</strong> 6d10+6 bludgeoning,</p>\n<p><strong>Ranged</strong> <span class=\"pf2-icon\">1</span> crash into the sea (range 120 feet, versatile P, water), <strong>Damage</strong> 6d6+6 bludgeoning</p>"
    },
    "rules": [],
    "slug": "vanguard-of-roaring-waters",
    "_migration": {
      "version": null,
      "lastMigration": null
    },
    "traits": {
      "otherTags": [],
      "value": [
        "hb_animist"
      ],
      "rarity": "common"
    },
    "publication": {
      "title": "",
      "authors": "",
      "license": "OGL",
      "remaster": false
    },
    "level": {
      "value": 1
    },
    "category": "classfeature",
    "onlyLevel1": false,
    "maxTakable": 1,
    "actionType": {
      "value": "passive"
    },
    "actions": {
      "value": null
    },
    "prerequisites": {
      "value": []
    },
    "location": null,
    "source": {
      "value": "War of Immortals Class Playtest"
    },
    "schema": {
      "version": 0.857,
      "lastMigration": null
    }
  },
  "img": "systems/pf2e/icons/spells/interstellar-void.webp",
  "flags": {},
  "_stats": {
    "systemId": "pf2e",
    "systemVersion": "5.4.2",
    "coreVersion": "12.327",
    "createdTime": 1693019816227,
    "modifiedTime": 1693750751327,
    "lastModifiedBy": "eXi1EIzPxP1KjPTb",
    "compendiumSource": null,
    "duplicateSource": null
  },
  "_id": "jGsDCNMB6zkZV4xX",
  "sort": 2900000,
  "ownership": {
    "default": 0,
    "CmdglLq38DpgHzdd": 3
  },
  "_key": "!items!jGsDCNMB6zkZV4xX"
}
